ep2_core/__init__.py
ep2_core/common.py
ep2_tutors/__init__.py
ep2_tutors/cli_eval.py
ep2_tutors/cli_ex_test.py
ep2_tutors/cli_util.py
ep2_tutors/ep2_eval.py
ep2_tutors/ep2_ex_test.py
ep2_tutors/ep2_util.py
ep2_tutors/idea_checkout.py
ep2_tutor_scripts-0.4.18.dist-info/METADATA
ep2_tutor_scripts-0.4.18.dist-info/WHEEL
ep2_tutor_scripts-0.4.18.dist-info/entry_points.txt
ep2_tutor_scripts-0.4.18.dist-info/top_level.txt
ep2_tutor_scripts-0.4.18.dist-info/RECORD
