Metadata-Version: 2.1
Name: ep2-tutor-scripts
Version: 0.4.18
Summary: UNKNOWN
Home-page: UNKNOWN
Author: Felix Resch
Author-email: felix.resch@tuwien.ac.at
License: UNKNOWN
Platform: UNKNOWN
Classifier: Programming Language :: Python :: 3
Classifier: License :: OSI Approved :: MIT License
Classifier: Operating System :: OS Independent
Requires-Python: >=3.6
Requires-Dist: python-gitlab (>=2.6.0)
Requires-Dist: click (>=7.0)
Requires-Dist: gitpython (>=3.1.0)
Requires-Dist: cheetah3 (>=3.2.0)
Requires-Dist: result (>=0.5.0)
Requires-Dist: getversion (>=1.0.2)
Requires-Dist: semver (>=2.13.0)
Requires-Dist: requests (>=2.23.0)
Requires-Dist: paramiko (>=2.7.2)
